todo_or_die/__init__.py
todo_or_die/exceptions.py
todo_or_die/main.py
todo_or_die/version.py
todo_or_die/helpers/__init__.py
todo_or_die/helpers/generate_message.py
todo_or_die/helpers/is_production.py
todo_or_die_python-0.1.1.dist-info/LICENSE
todo_or_die_python-0.1.1.dist-info/METADATA
todo_or_die_python-0.1.1.dist-info/WHEEL
todo_or_die_python-0.1.1.dist-info/top_level.txt
todo_or_die_python-0.1.1.dist-info/RECORD
