Metadata-Version: 2.1
Name: todo-or-die-python
Version: 0.1.1
Summary: Halt code if your TODO is passed due
Home-page: https://github.com/walshyb/todo-or-die-python
Author: Brandon Walsh
Author-email: bmwalshy@gmail.com
License: UNKNOWN
Project-URL: Bug Tracker, https://github.com/walshyb/todo-or-die-python/issues
Platform: UNKNOWN
Classifier: Programming Language :: Python :: 3
Classifier: License :: OSI Approved :: MIT License
Classifier: Operating System :: OS Independent
Requires-Python: >=3.6
License-File: LICENSE
